remrpc/__init__.py
remrpc/uniqueid.py
remrpc-0.1.11.dist-info/LICENSE
remrpc-0.1.11.dist-info/METADATA
remrpc-0.1.11.dist-info/WHEEL
remrpc-0.1.11.dist-info/top_level.txt
remrpc-0.1.11.dist-info/RECORD
